pytest_pyodide/__init__.py
pytest_pyodide/_decorator_in_pyodide.py
pytest_pyodide/config.py
pytest_pyodide/copy_files_to_pyodide.py
pytest_pyodide/decorator.py
pytest_pyodide/doctest.py
pytest_pyodide/fixture.py
pytest_pyodide/hook.py
pytest_pyodide/hypothesis.py
pytest_pyodide/node_test_driver.js
pytest_pyodide/run_tests_inside_pyodide.py
pytest_pyodide/runner.py
pytest_pyodide/server.py
pytest_pyodide/utils.py
pytest_pyodide/_templates/module_test.html
pytest_pyodide/_templates/module_webworker_dev.js
pytest_pyodide/_templates/test.html
pytest_pyodide/_templates/webworker_dev.js
pytest_pyodide-0.58.10.dist-info/METADATA
pytest_pyodide-0.58.10.dist-info/WHEEL
pytest_pyodide-0.58.10.dist-info/entry_points.txt
pytest_pyodide-0.58.10.dist-info/licenses/LICENSE
pytest_pyodide-0.58.10.dist-info/RECORD
