Metadata-Version: 2.4
Name: pytest-pyodide
Version: 0.58.10
Summary: Pytest plugin for testing applications that use Pyodide
Project-URL: Homepage, https://github.com/pyodide/pytest-pyodide
Project-URL: Repository, https://github.com/pyodide/pytest-pyodide
Project-URL: Changelog, https://github.com/pyodide/pytest-pyodide/blob/main/CHANGELOG.md
License: Mozilla Public License Version 2.0
License-File: LICENSE
Classifier: Framework :: Pytest
Classifier: License :: OSI Approved :: Mozilla Public License 2.0 (MPL 2.0)
Classifier: Operating System :: OS Independent
Classifier: Programming Language :: Python :: 3
Requires-Python: >=3.11
Requires-Dist: hypothesis
Requires-Dist: pexpect
Requires-Dist: playwright
Requires-Dist: pytest
Requires-Dist: pytest-asyncio
Requires-Dist: selenium
Requires-Dist: tblib>=3
Provides-Extra: test
Requires-Dist: build; extra == 'test'
Requires-Dist: pytest-cov; extra == 'test'
Requires-Dist: requests; extra == 'test'
Requires-Dist: selenium<4.21.0; extra == 'test'
